guardduty_runbooks/__init__.py
guardduty_runbooks/cli.py
guardduty_runbooks/guardduty.py
guardduty_runbooks/utils.py
guardduty_runbooks-0.3.0.dist-info/LICENSE.md
guardduty_runbooks-0.3.0.dist-info/METADATA
guardduty_runbooks-0.3.0.dist-info/WHEEL
guardduty_runbooks-0.3.0.dist-info/entry_points.txt
guardduty_runbooks-0.3.0.dist-info/top_level.txt
guardduty_runbooks-0.3.0.dist-info/RECORD
