Metadata-Version: 2.1
Name: guardduty-runbooks
Version: 0.3.0
Summary: GuardDuty Runbook Generator
Author-email: Dustin Whited <dustin.whited@aquia.us>
Project-URL: Homepage, https://aquia.us
Project-URL: Repository, https://github.com/aquia-inc/aws-guardduty-runbook-generator
Requires-Python: >=3.9
License-File: LICENSE.md
Requires-Dist: markdownify >=0.12.1
Requires-Dist: docopt >=0.6.2
Requires-Dist: requests >=2.32.3
Requires-Dist: beautifulsoup4 >=4.12.3
